{
  "success": true,
  "code": 200,
  "message": "정상적으로 요청이 처리되었습니당",
  "results": [
    {
      "id": 1,
      "title": "2인분 부대찌개 밀키트",
      "image": "https://www.foodbank.co.kr/news/photo/202201/62407_19908_1226.jpg",
      "images": [
        "https://picsum.photos/300/200?random=50",
        "https://picsum.photos/400/300?random=5001"
      ],
      "discount": 30,
      "price": 15900,
      "originalPrice": 22900,
      "rating": 4.8,
      "reviewCount": 1234,
      "likes": 1987,
      "salesCount": 1234,
      "category": "bakingProducts",
      "description": "달콤하고 부드러운 맛의 프리미엄 화이트 초콜릿입니다.",
      "detailInfo": {
        "brand": "초콜릿킹",
        "origin": "수입산",
        "weight": "200g",
        "storage": "상온보관"
      },
      "tags": ["화이트초콜릿", "달콤", "프리미엄"]
    },
    {
      "id": 2,
      "title": "한식키트 2종 (떡볶이 & 부대찌개)",
      "image": "https://cdn-dantats.stunning.kr/prod/portfolios/c66aaf60-74e0-4814-b552-cd3020d43afd/covers/order_sub_2865765_1_211012212956.png.small?s=800x800&t=crop&q=80&f=webp",
      "images": [
        "https://picsum.photos/300/200?random=50",
        "https://picsum.photos/400/300?random=5001"
      ],
      "discount": 4,
      "price": 21900,
      "originalPrice": 22900,
      "rating": 4.5,
      "reviewCount": 1234,
      "likes": 1987,
      "salesCount": 334,
      "category": "bakingProducts",
      "description": "달콤하고 부드러운 맛의 프리미엄 화이트 초콜릿입니다.",
      "detailInfo": {
        "brand": "초콜릿킹",
        "origin": "수입산",
        "weight": "200g",
        "storage": "상온보관"
      },
      "tags": ["화이트초콜릿", "달콤", "프리미엄"]
    },
    {
      "id": 3,
      "title": "곰탕 밀키트 1인분",
      "image": "https://newsimg.hankookilbo.com/cms/articlerelease/2021/07/31/f24809e6-ed0d-486e-a3cf-2cf42c103c56.jpg",
      "images": [
        "https://picsum.photos/300/200?random=50",
        "https://picsum.photos/400/300?random=5001"
      ],
      "discount": 50,
      "price": 15900,
      "originalPrice": 21800,
      "rating": 5,
      "reviewCount": 2256,
      "likes": 1987,
      "salesCount": 1234,
      "category": "bakingProducts",
      "description": "달콤하고 부드러운 맛의 프리미엄 화이트 초콜릿입니다.",
      "detailInfo": {
        "brand": "초콜릿킹",
        "origin": "수입산",
        "weight": "200g",
        "storage": "상온보관"
      },
      "tags": ["화이트초콜릿", "달콤", "프리미엄"]
    },
    {
      "id": 4,
      "title": "닭갈비 2종 택 1",
      "image": "https://halicrty8541.edge.naverncp.com/data/mall_data/images/product/00/00/00/21/33/m_0000002133.gif",
      "images": [
        "https://picsum.photos/300/200?random=50",
        "https://picsum.photos/400/300?random=5001"
      ],
      "discount": 68,
      "price": 15900,
      "originalPrice": 34900,
      "rating": 3.7,
      "reviewCount": 45556,
      "likes": 1987,
      "salesCount": 1234,
      "category": "bakingProducts",
      "description": "달콤하고 부드러운 맛의 프리미엄 화이트 초콜릿입니다.",
      "detailInfo": {
        "brand": "초콜릿킹",
        "origin": "수입산",
        "weight": "200g",
        "storage": "상온보관"
      },
      "tags": ["화이트초콜릿", "달콤", "프리미엄"]
    }
  ]
}
